aliyunsdkeipanycast/__init__.py
aliyunsdkeipanycast/endpoint.py
aliyunsdkeipanycast/request/__init__.py
aliyunsdkeipanycast/request/v20200309/AllocateAnycastEipAddressRequest.py
aliyunsdkeipanycast/request/v20200309/AssociateAnycastEipAddressRequest.py
aliyunsdkeipanycast/request/v20200309/DescribeAnycastEipAddressRequest.py
aliyunsdkeipanycast/request/v20200309/DescribeAnycastPopLocationsRequest.py
aliyunsdkeipanycast/request/v20200309/DescribeAnycastServerRegionsRequest.py
aliyunsdkeipanycast/request/v20200309/ListAnycastEipAddressesRequest.py
aliyunsdkeipanycast/request/v20200309/ListTagResourcesRequest.py
aliyunsdkeipanycast/request/v20200309/ModifyAnycastEipAddressAttributeRequest.py
aliyunsdkeipanycast/request/v20200309/ModifyAnycastEipAddressSpecRequest.py
aliyunsdkeipanycast/request/v20200309/ReleaseAnycastEipAddressRequest.py
aliyunsdkeipanycast/request/v20200309/TagResourcesRequest.py
aliyunsdkeipanycast/request/v20200309/UnassociateAnycastEipAddressRequest.py
aliyunsdkeipanycast/request/v20200309/UntagResourcesRequest.py
aliyunsdkeipanycast/request/v20200309/UpdateAnycastEipAddressAssociationsRequest.py
aliyunsdkeipanycast/request/v20200309/__init__.py
aliyun_python_sdk_eipanycast-1.0.5.dist-info/LICENSE
aliyun_python_sdk_eipanycast-1.0.5.dist-info/METADATA
aliyun_python_sdk_eipanycast-1.0.5.dist-info/WHEEL
aliyun_python_sdk_eipanycast-1.0.5.dist-info/top_level.txt
aliyun_python_sdk_eipanycast-1.0.5.dist-info/RECORD
